{
  "_id": "multiple-choice-2.df6",
  "_rev": 1,
  "data_format_version": 6,
  "activity": {
    "title": "Multiple Choice 2",
    "url": "/shared/multiple-choice-2",
    "owner": "shared",
    "pages": [
      "/shared/multiple-choice-2/page/1-first-page"
    ],
    "axes": [
      "/shared/multiple-choice-2/axes/1",
      "/shared/multiple-choice-2/axes/2"
    ]
  },
  "pages": [
    {
      "name": "First Page",
      "url": "/shared/multiple-choice-2/page/1-first-page",
      "activity": "/shared/multiple-choice-2",
      "index": 1,
      "introText": "<p>This is an example page.</p>",
      "steps": [
        "/shared/multiple-choice-2/page/1-first-page/step/1",
        "/shared/multiple-choice-2/page/1-first-page/step/2",
        "/shared/multiple-choice-2/page/1-first-page/step/3",
        "/shared/multiple-choice-2/page/1-first-page/step/4"
      ],
      "firstStep": "/shared/multiple-choice-2/page/1-first-page/step/1",
      "contextVars": []
    }
  ],
  "steps": [
    {
      "url": "/shared/multiple-choice-2/page/1-first-page/step/1",
      "activityPage": "/shared/multiple-choice-2/page/1-first-page",
      "beforeText": "<p>Which of the following choices is choice \"B\"?</p>",
      "paneConfig": "single",
      "panes": {
        "single": {
          "type": "graph",
          "title": "The Graph",
          "xAxis": "/shared/multiple-choice-2/axes/1",
          "yAxis": "/shared/multiple-choice-2/axes/2",
          "annotations": [],
          "highlightedAnnotations": [],
          "data": [
            "datadef-1"
          ],
          "legends": [
            "datadef-1"
          ],
          "activeDatadefs": [
            "datadef-1"
          ]
        }
      },
      "submitButtonTitle": "Check My Answer",
      "defaultBranch": "/shared/multiple-choice-2/page/1-first-page/step/1",
      "responseTemplate": "/shared/multiple-choice-2/response-templates/multiple-choice-1",
      "submissibilityCriterion": [
        "isNumeric",
        [
          "responseField",
          1
        ]
      ],
      "responseBranches": [
        {
          "criterion": [
            "=",
            [
              "responseField",
              1
            ],
            2
          ],
          "step": "/shared/multiple-choice-2/page/1-first-page/step/4"
        },
        {
          "criterion": [
            "=",
            [
              "responseField",
              1
            ],
            1
          ],
          "step": "/shared/multiple-choice-2/page/1-first-page/step/2"
        },
        {
          "criterion": [
            "=",
            [
              "responseField",
              1
            ],
            3
          ],
          "step": "/shared/multiple-choice-2/page/1-first-page/step/3"
        }
      ],
      "isFinalStep": false
    },
    {
      "url": "/shared/multiple-choice-2/page/1-first-page/step/2",
      "activityPage": "/shared/multiple-choice-2/page/1-first-page",
      "beforeText": "<p>Try to think! What is the difference between the letters A and B. Which would win in a fair fight, if Optimus Prime and Grimlock helped B? Try again.</p>",
      "paneConfig": "single",
      "panes": {
        "single": {
          "type": "graph",
          "title": "The Graph",
          "xAxis": "/shared/multiple-choice-2/axes/1",
          "yAxis": "/shared/multiple-choice-2/axes/2",
          "annotations": [],
          "highlightedAnnotations": [],
          "data": [
            "datadef-1"
          ],
          "legends": [
            "datadef-1"
          ],
          "activeDatadefs": [
            "datadef-1"
          ]
        }
      },
      "submitButtonTitle": "Check My Answer",
      "defaultBranch": "/shared/multiple-choice-2/page/1-first-page/step/2",
      "responseTemplate": "/shared/multiple-choice-2/response-templates/multiple-choice-1",
      "submissibilityCriterion": [
        "isNumeric",
        [
          "responseField",
          1
        ]
      ],
      "responseBranches": [
        {
          "criterion": [
            "=",
            [
              "responseField",
              1
            ],
            2
          ],
          "step": "/shared/multiple-choice-2/page/1-first-page/step/4"
        },
        {
          "criterion": [
            "=",
            [
              "responseField",
              1
            ],
            1
          ],
          "step": "/shared/multiple-choice-2/page/1-first-page/step/2"
        },
        {
          "criterion": [
            "=",
            [
              "responseField",
              1
            ],
            3
          ],
          "step": "/shared/multiple-choice-2/page/1-first-page/step/3"
        }
      ],
      "isFinalStep": false
    },
    {
      "url": "/shared/multiple-choice-2/page/1-first-page/step/3",
      "activityPage": "/shared/multiple-choice-2/page/1-first-page",
      "beforeText": "<p>Now, really. What do you think makes C like B? Ask yourself, does C have B envy? Then try again.</p>",
      "paneConfig": "single",
      "panes": {
        "single": {
          "type": "graph",
          "title": "The Graph",
          "xAxis": "/shared/multiple-choice-2/axes/1",
          "yAxis": "/shared/multiple-choice-2/axes/2",
          "annotations": [],
          "highlightedAnnotations": [],
          "data": [
            "datadef-1"
          ],
          "legends": [
            "datadef-1"
          ],
          "activeDatadefs": [
            "datadef-1"
          ]
        }
      },
      "submitButtonTitle": "Check My Answer",
      "defaultBranch": "/shared/multiple-choice-2/page/1-first-page/step/3",
      "responseTemplate": "/shared/multiple-choice-2/response-templates/multiple-choice-1",
      "submissibilityCriterion": [
        "isNumeric",
        [
          "responseField",
          1
        ]
      ],
      "responseBranches": [
        {
          "criterion": [
            "=",
            [
              "responseField",
              1
            ],
            2
          ],
          "step": "/shared/multiple-choice-2/page/1-first-page/step/4"
        },
        {
          "criterion": [
            "=",
            [
              "responseField",
              1
            ],
            1
          ],
          "step": "/shared/multiple-choice-2/page/1-first-page/step/2"
        },
        {
          "criterion": [
            "=",
            [
              "responseField",
              1
            ],
            3
          ],
          "step": "/shared/multiple-choice-2/page/1-first-page/step/3"
        }
      ],
      "isFinalStep": false
    },
    {
      "url": "/shared/multiple-choice-2/page/1-first-page/step/4",
      "activityPage": "/shared/multiple-choice-2/page/1-first-page",
      "beforeText": "<p>That's right. I wanted choice B, you gave it to me.</p>",
      "paneConfig": "single",
      "panes": {
        "single": {
          "type": "graph",
          "title": "The Graph",
          "xAxis": "/shared/multiple-choice-2/axes/1",
          "yAxis": "/shared/multiple-choice-2/axes/2",
          "annotations": [],
          "highlightedAnnotations": [],
          "data": [
            "datadef-1"
          ],
          "legends": [
            "datadef-1"
          ],
          "activeDatadefs": [
            "datadef-1"
          ]
        }
      },
      "isFinalStep": true,
      "nextButtonShouldSubmit": true
    }
  ],
  "responseTemplates": [
    {
      "url": "/shared/multiple-choice-2/response-templates/multiple-choice-1",
      "templateString": "",
      "fieldChoicesList": [
        [
          "Choice A",
          "Choice B",
          "Choice C"
        ]
      ],
      "initialValues": [
        ""
      ],
      "fieldTypes": [
        "multiplechoice"
      ]
    }
  ],
  "axes": [
    {
      "url": "/shared/multiple-choice-2/axes/1",
      "units": "/shared/multiple-choice-2/units/seconds",
      "min": 0,
      "max": 10,
      "nSteps": 10,
      "label": "Time"
    },
    {
      "url": "/shared/multiple-choice-2/axes/2",
      "units": "/shared/multiple-choice-2/units/meters",
      "min": 0,
      "max": 100,
      "nSteps": 10,
      "label": "Distance"
    }
  ],
  "datadefs": [
    {
      "type": "UnorderedDataPoints",
      "records": [
        {
          "url": "/shared/multiple-choice-2/datadefs/datadef-1",
          "name": "datadef-1",
          "activity": "/shared/multiple-choice-2",
          "xUnits": "/shared/multiple-choice-2/units/seconds",
          "yUnits": "/shared/multiple-choice-2/units/meters",
          "points": [
            [
              0,
              0
            ],
            [
              1,
              10
            ],
            [
              2,
              20
            ],
            [
              3,
              30
            ],
            [
              4,
              40
            ]
          ],
          "lineSnapDistance": 0
        }
      ]
    }
  ],
  "tags": [],
  "annotations": [],
  "variables": [],
  "units": [
    {
      "url": "/shared/multiple-choice-2/units/meters",
      "activity": "/shared/multiple-choice-2",
      "name": "meter",
      "abbreviation": "m",
      "pluralName": "meters"
    },
    {
      "url": "/shared/multiple-choice-2/units/minutes",
      "activity": "/shared/multiple-choice-2",
      "name": "minute",
      "abbreviation": "m",
      "pluralName": "minutes"
    },
    {
      "url": "/shared/multiple-choice-2/units/meters per second",
      "activity": "/shared/multiple-choice-2",
      "name": "meters per second",
      "abbreviation": "m/s",
      "pluralName": "meters per second"
    },
    {
      "url": "/shared/multiple-choice-2/units/seconds",
      "activity": "/shared/multiple-choice-2",
      "name": "second",
      "abbreviation": "s",
      "pluralName": "seconds"
    }
  ]
}
